Metadata-Version: 2.1
Name: odoo8-addon-l10n-ch-sepa
Version: 8.0.1.0.1
Summary: Generate pain.001 Credit Transfert Files for your payments
Home-page: UNKNOWN
Author: Camptocamp,Odoo Community Association (OCA)
Author-email: support@odoo-community.org
License: AGPL-3
Platform: UNKNOWN
Classifier: Programming Language :: Python
Classifier: Framework :: Odoo
Classifier: License :: OSI Approved :: GNU Affero General Public License v3
Requires-Python: ~=2.7
Requires-Dist: odoo8-addon-l10n-ch-base-bank
Requires-Dist: odoo8-addon-l10n-ch-payment-slip
Requires-Dist: odoo (<9.0a,>=8.0a)
